grafana_calendar_annotator/__init__.py
grafana_calendar_annotator/cli.py
grafana_calendar_annotator/lib.py
grafana_calendar_annotator-0.1.2.dist-info/entry_points.txt
grafana_calendar_annotator-0.1.2.dist-info/LICENSE.txt
grafana_calendar_annotator-0.1.2.dist-info/WHEEL
grafana_calendar_annotator-0.1.2.dist-info/METADATA
grafana_calendar_annotator-0.1.2.dist-info/RECORD
