Metadata-Version: 2.1
Name: grafana-calendar-annotator
Version: 0.1.2
Summary: Generate Grafana Annotations from calendar events
Home-page: https://github.com/cam-barts/grafana-calendar-annotator
License: MIT
Keywords: grafana,monitoring,annotations,calendar,ics,ical
Author: Cam
Author-email: camerond.barts@gmail.com
Requires-Python: >=3.7,<3.10
Classifier: Environment :: Console
Classifier: License :: OSI Approved :: MIT License
Classifier: Programming Language :: Python :: 3
Classifier: Programming Language :: Python :: 3.7
Classifier: Programming Language :: Python :: 3.8
Classifier: Programming Language :: Python :: 3.9
Classifier: Programming Language :: Python :: 3
Classifier: Topic :: Home Automation
Classifier: Topic :: Software Development :: Libraries :: Python Modules
Classifier: Topic :: System :: Monitoring
Classifier: Topic :: Utilities
Requires-Dist: ics (>=0.7.2,<0.8.0)
Requires-Dist: python-decouple (>=3.6,<4.0)
Requires-Dist: requests (>=2.28.1,<3.0.0)
Requires-Dist: rich-click (>=1.5.2,<2.0.0)
Project-URL: Bug Tracker, https://github.com/cam-barts/grafana-calendar-annotator/issues
Project-URL: Contributing, https://github.com/cam-barts/grafana-calendar-annotator/blob/main/CONTRIBUTING.md
Project-URL: Code Of Conduct, https://github.com/cam-barts/grafana-calendar-annotator/blob/main/CODE_OF_CONDUCT.md
Project-URL: Repository, https://github.com/cam-barts/grafana-calendar-annotator
